{
  "summary": {
    "cnn_classifier": {
      "seeds": 1,
      "param_count": 9473,
      "accuracy_mean": 0.9916666666666667,
      "accuracy_std": 0.0,
      "precision_mean": 0.9928366762177651,
      "recall_mean": 0.990234375,
      "train_time_mean_s": 0.28983163833618164,
      "confusion_matrix": [
        [
          688,
          0
        ],
        [
          10,
          502
        ]
      ],
      "roc_auc_mean": 1.0
    },
    "photonic_classifier": {
      "seeds": 1,
      "param_count": 71,
      "accuracy_mean": 0.935,
      "accuracy_std": 0.0,
      "precision_mean": 0.9490861618798956,
      "recall_mean": 0.923828125,
      "train_time_mean_s": 0.20451641082763672,
      "confusion_matrix": [
        [
          688,
          0
        ],
        [
          78,
          434
        ]
      ],
      "roc_auc_mean": 0.9990319540334301
    },
    "qcnn_classifier": {
      "seeds": 1,
      "param_count": 25,
      "accuracy_mean": 0.5858333333333333,
      "accuracy_std": 0.0,
      "precision_mean": 0.790295358649789,
      "recall_mean": 0.5146484375,
      "train_time_mean_s": 84.74606156349182,
      "confusion_matrix": [
        [
          688,
          0
        ],
        [
          497,
          15
        ]
      ],
      "roc_auc_mean": 0.9368442269258721
    }
  },
  "per_seed": {
    "cnn_classifier": [
      {
        "name": "cnn_classifier",
        "epochs": [
          {
            "loss": 0.5907099149908338,
            "accuracy": 0.9933333333333333,
            "precision": 0.9942528735632183,
            "recall": 0.9921875,
            "time_s": 0.06173419952392578
          },
          {
            "loss": 0.2938695125920432,
            "accuracy": 0.9916666666666667,
            "precision": 0.9928366762177651,
            "recall": 0.990234375,
            "time_s": 0.06861138343811035
          },
          {
            "loss": 0.1030476536495345,
            "accuracy": 0.9916666666666667,
            "precision": 0.9928366762177651,
            "recall": 0.990234375,
            "time_s": 0.07116293907165527
          }
        ],
        "final_accuracy": 0.9916666666666667,
        "final_precision": 0.9928366762177651,
        "final_recall": 0.990234375,
        "confusion_matrix": [
          [
            688,
            0
          ],
          [
            10,
            502
          ]
        ],
        "param_count": 9473,
        "train_time_s": 0.28983163833618164,
        "roc_auc": 1.0,
        "roc_curve": {
          "fpr": [
            0.0,
            0.0,
            0.0,
            0.0,
            0.0,
            0.0,
            0.0,
            0.0,
            0.0,
            0.0,
            0.0,
            0.0,
            0.0,
            0.0,
            1.0
          ],
          "tpr": [
            0.0,
            0.001953125,
            0.005859375,
            0.0234375,
            0.02734375,
            0.048828125,
            0.056640625,
            0.080078125,
            0.083984375,
            0.16015625,
            0.1640625,
            0.228515625,
            0.232421875,
            1.0,
            1.0
          ],
          "thresholds": [
            Infinity,
            0.9999394416809082,
            0.9999363422393799,
            0.9998639822006226,
            0.9998612403869629,
            0.9997444748878479,
            0.9997429251670837,
            0.9989715814590454,
            0.9989714622497559,
            0.9971215128898621,
            0.9970836043357849,
            0.9966868758201599,
            0.9966694712638855,
            0.38829755783081055,
            3.3602304029045627e-05
          ]
        }
      }
    ],
    "photonic_classifier": [
      {
        "name": "photonic_classifier",
        "epochs": [
          {
            "loss": 0.6355626497949872,
            "accuracy": 0.7125,
            "precision": 0.8330106485963213,
            "recall": 0.6630859375,
            "time_s": 0.03805422782897949
          },
          {
            "loss": 0.5299718534946442,
            "accuracy": 0.9125,
            "precision": 0.9337957124842371,
            "recall": 0.8974609375,
            "time_s": 0.036373138427734375
          },
          {
            "loss": 0.4476580241748265,
            "accuracy": 0.935,
            "precision": 0.9490861618798956,
            "recall": 0.923828125,
            "time_s": 0.036835432052612305
          }
        ],
        "final_accuracy": 0.935,
        "final_precision": 0.9490861618798956,
        "final_recall": 0.923828125,
        "confusion_matrix": [
          [
            688,
            0
          ],
          [
            78,
            434
          ]
        ],
        "param_count": 71,
        "train_time_s": 0.20451641082763672,
        "roc_auc": 0.9990319540334301,
        "roc_curve": {
          "fpr": [
            0.0,
            0.0,
            0.0,
            0.0,
            0.0,
            0.0,
            0.0,
            0.0014534883720930232,
            0.0014534883720930232,
            0.0029069767441860465,
            0.0029069767441860465,
            0.00436046511627907,
            0.00436046511627907,
            0.005813953488372093,
            0.005813953488372093,
            0.00872093023255814,
            0.00872093023255814,
            0.02180232558139535,
            0.02180232558139535,
            1.0
          ],
          "tpr": [
            0.0,
            0.001953125,
            0.44140625,
            0.4453125,
            0.486328125,
            0.490234375,
            0.919921875,
            0.919921875,
            0.927734375,
            0.927734375,
            0.935546875,
            0.935546875,
            0.9375,
            0.9375,
            0.947265625,
            0.947265625,
            0.96875,
            0.96875,
            1.0,
            1.0
          ],
          "thresholds": [
            Infinity,
            0.7517501711845398,
            0.6193167567253113,
            0.6193127632141113,
            0.6190330386161804,
            0.6190148591995239,
            0.4765591621398926,
            0.4764000177383423,
            0.47112664580345154,
            0.4710001051425934,
            0.4665353000164032,
            0.46640193462371826,
            0.466067373752594,
            0.46570706367492676,
            0.4593323767185211,
            0.45687296986579895,
            0.4490482807159424,
            0.4141719937324524,
            0.3398584723472595,
            0.2361694872379303
          ]
        }
      }
    ],
    "qcnn_classifier": [
      {
        "name": "qcnn_classifier",
        "epochs": [
          {
            "loss": 0.6680843979971749,
            "accuracy": 0.5733333333333334,
            "precision": 0.2866666666666667,
            "recall": 0.5,
            "time_s": 12.479666948318481
          },
          {
            "loss": 0.6510208766801017,
            "accuracy": 0.5833333333333334,
            "precision": 0.7895622895622896,
            "recall": 0.51171875,
            "time_s": 13.8387770652771
          },
          {
            "loss": 0.6313410087994167,
            "accuracy": 0.5858333333333333,
            "precision": 0.790295358649789,
            "recall": 0.5146484375,
            "time_s": 16.08887529373169
          }
        ],
        "final_accuracy": 0.5858333333333333,
        "final_precision": 0.790295358649789,
        "final_recall": 0.5146484375,
        "confusion_matrix": [
          [
            688,
            0
          ],
          [
            497,
            15
          ]
        ],
        "param_count": 25,
        "train_time_s": 84.74606156349182,
        "roc_auc": 0.9368442269258721,
        "roc_curve": {
          "fpr": [
            0.0,
            0.0,
            0.0,
            0.0029069767441860465,
            0.0029069767441860465,
            0.00872093023255814,
            0.00872093023255814,
            0.010174418604651164,
            0.010174418604651164,
            0.01308139534883721,
            0.01308139534883721,
            0.014534883720930232,
            0.014534883720930232,
            0.015988372093023256,
            0.015988372093023256,
            0.01744186046511628,
            0.01744186046511628,
            0.020348837209302327,
            0.020348837209302327,
            0.023255813953488372,
            0.023255813953488372,
            0.024709302325581394,
            0.024709302325581394,
            0.02616279069767442,
            0.02616279069767442,
            0.029069767441860465,
            0.029069767441860465,
            0.03488372093023256,
            0.03488372093023256,
            0.03924418604651163,
            0.03924418604651163,
            0.040697674418604654,
            0.040697674418604654,
            0.04215116279069767,
            0.04215116279069767,
            0.046511627906976744,
            0.046511627906976744,
            0.04796511627906977,
            0.04796511627906977,
            0.04941860465116279,
            0.04941860465116279,
            0.050872093023255814,
            0.050872093023255814,
            0.05232558139534884,
            0.05232558139534884,
            0.05377906976744186,
            0.05377906976744186,
            0.055232558139534885,
            0.055232558139534885,
            0.056686046511627904,
            0.056686046511627904,
            0.05813953488372093,
            0.05813953488372093,
            0.059593023255813955,
            0.059593023255813955,
            0.061046511627906974,
            0.061046511627906974,
            0.0625,
            0.0625,
            0.06686046511627906,
            0.06686046511627906,
            0.06831395348837209,
            0.06831395348837209,
            0.07267441860465117,
            0.07267441860465117,
            0.07703488372093023,
            0.07703488372093023,
            0.07848837209302326,
            0.07848837209302326,
            0.07994186046511628,
            0.07994186046511628,
            0.08139534883720931,
            0.08139534883720931,
            0.08430232558139535,
            0.08430232558139535,
            0.08575581395348837,
            0.08575581395348837,
            0.0872093023255814,
            0.0872093023255814,
            0.08866279069767442,
            0.08866279069767442,
            0.09011627906976744,
            0.09011627906976744,
            0.09156976744186046,
            0.09156976744186046,
            0.09302325581395349,
            0.09302325581395349,
            0.09593023255813954,
            0.09593023255813954,
            0.09738372093023256,
            0.09738372093023256,
            0.09883720930232558,
            0.09883720930232558,
            0.1002906976744186,
            0.1002906976744186,
            0.10174418604651163,
            0.10174418604651163,
            0.10610465116279069,
            0.10610465116279069,
            0.10755813953488372,
            0.10755813953488372,
            0.10901162790697674,
            0.10901162790697674,
            0.11046511627906977,
            0.11046511627906977,
            0.1119186046511628,
            0.1119186046511628,
            0.11337209302325581,
            0.11337209302325581,
            0.11482558139534883,
            0.11482558139534883,
            0.11627906976744186,
            0.11627906976744186,
            0.11627906976744186,
            0.11773255813953488,
            0.11773255813953488,
            0.11918604651162791,
            0.11918604651162791,
            0.20784883720930233,
            0.20784883720930233,
            0.20930232558139536,
            0.20930232558139536,
            0.21075581395348839,
            0.21075581395348839,
            0.21220930232558138,
            0.21220930232558138,
            0.2136627906976744,
            0.2136627906976744,
            0.22529069767441862,
            0.22529069767441862,
            0.22965116279069767,
            0.22965116279069767,
            0.23255813953488372,
            0.23255813953488372,
            0.23401162790697674,
            0.23401162790697674,
            1.0
          ],
          "tpr": [
            0.0,
            0.001953125,
            0.2578125,
            0.2578125,
            0.263671875,
            0.263671875,
            0.271484375,
            0.271484375,
            0.28125,
            0.28125,
            0.29296875,
            0.29296875,
            0.3046875,
            0.3046875,
            0.306640625,
            0.306640625,
            0.3125,
            0.3125,
            0.314453125,
            0.314453125,
            0.322265625,
            0.322265625,
            0.3828125,
            0.3828125,
            0.384765625,
            0.384765625,
            0.38671875,
            0.38671875,
            0.390625,
            0.390625,
            0.396484375,
            0.396484375,
            0.3984375,
            0.3984375,
            0.431640625,
            0.431640625,
            0.435546875,
            0.435546875,
            0.4375,
            0.4375,
            0.44140625,
            0.44140625,
            0.44921875,
            0.44921875,
            0.451171875,
            0.451171875,
            0.455078125,
            0.455078125,
            0.46484375,
            0.46484375,
            0.478515625,
            0.478515625,
            0.48046875,
            0.48046875,
            0.505859375,
            0.505859375,
            0.5078125,
            0.5078125,
            0.509765625,
            0.509765625,
            0.53125,
            0.53125,
            0.537109375,
            0.537109375,
            0.5546875,
            0.5546875,
            0.55859375,
            0.55859375,
            0.560546875,
            0.560546875,
            0.564453125,
            0.564453125,
            0.5703125,
            0.5703125,
            0.5859375,
            0.5859375,
            0.59375,
            0.59375,
            0.603515625,
            0.603515625,
            0.60546875,
            0.60546875,
            0.607421875,
            0.607421875,
            0.65234375,
            0.65234375,
            0.6953125,
            0.6953125,
            0.72265625,
            0.72265625,
            0.744140625,
            0.744140625,
            0.748046875,
            0.748046875,
            0.76171875,
            0.76171875,
            0.771484375,
            0.771484375,
            0.78515625,
            0.78515625,
            0.787109375,
            0.787109375,
            0.791015625,
            0.791015625,
            0.8203125,
            0.8203125,
            0.82421875,
            0.82421875,
            0.830078125,
            0.830078125,
            0.8359375,
            0.8359375,
            0.892578125,
            0.896484375,
            0.896484375,
            0.912109375,
            0.912109375,
            0.94921875,
            0.94921875,
            0.951171875,
            0.951171875,
            0.9609375,
            0.9609375,
            0.982421875,
            0.982421875,
            0.984375,
            0.984375,
            0.986328125,
            0.986328125,
            0.990234375,
            0.990234375,
            0.9921875,
            0.9921875,
            0.99609375,
            0.99609375,
            1.0,
            1.0
          ],
          "thresholds": [
            Infinity,
            0.5536256432533264,
            0.45904460549354553,
            0.4586176872253418,
            0.45833906531333923,
            0.45788654685020447,
            0.45778441429138184,
            0.45763176679611206,
            0.45732319355010986,
            0.45718520879745483,
            0.4568105638027191,
            0.4568012058734894,
            0.4562450349330902,
            0.4560690224170685,
            0.45603322982788086,
            0.45594409108161926,
            0.455437570810318,
            0.4551394581794739,
            0.45509159564971924,
            0.45501336455345154,
            0.4545062780380249,
            0.4541310966014862,
            0.4526920020580292,
            0.4526098668575287,
            0.45240721106529236,
            0.4523763358592987,
            0.45197030901908875,
            0.45130565762519836,
            0.4512391984462738,
            0.4509273171424866,
            0.45050400495529175,
            0.450320303440094,
            0.450300008058548,
            0.4502059519290924,
            0.44851401448249817,
            0.4483237564563751,
            0.4482235610485077,
            0.44817274808883667,
            0.4481503963470459,
            0.4481074810028076,
            0.4480305314064026,
            0.44796687364578247,
            0.44771403074264526,
            0.4476964771747589,
            0.44768428802490234,
            0.44764095544815063,
            0.44750353693962097,
            0.447314977645874,
            0.44675928354263306,
            0.44673892855644226,
            0.4461512863636017,
            0.44605696201324463,
            0.4460383653640747,
            0.446014940738678,
            0.44561898708343506,
            0.4456140697002411,
            0.4456017017364502,
            0.4455946385860443,
            0.4454857409000397,
            0.4452346861362457,
            0.44488492608070374,
            0.44488126039505005,
            0.44453781843185425,
            0.44444769620895386,
            0.4436837434768677,
            0.44352391362190247,
            0.4434918165206909,
            0.44342097640037537,
            0.443329781293869,
            0.44328901171684265,
            0.4432617425918579,
            0.44325289130210876,
            0.44309714436531067,
            0.4430180490016937,
            0.4427647590637207,
            0.4427640736103058,
            0.4425639808177948,
            0.44252410531044006,
            0.44237029552459717,
            0.4423469007015228,
            0.44230568408966064,
            0.44227802753448486,
            0.44218912720680237,
            0.44216689467430115,
            0.44173893332481384,
            0.4417245388031006,
            0.4410927891731262,
            0.4410700798034668,
            0.4406863749027252,
            0.4406788647174835,
            0.44041964411735535,
            0.44041845202445984,
            0.4403761327266693,
            0.44034650921821594,
            0.44013017416000366,
            0.44011345505714417,
            0.43961021304130554,
            0.4390246868133545,
            0.4385162889957428,
            0.43837037682533264,
            0.43823421001434326,
            0.438188374042511,
            0.4379768669605255,
            0.4379758834838867,
            0.4369542896747589,
            0.4366605579853058,
            0.43655815720558167,
            0.43624746799468994,
            0.4355374574661255,
            0.4353209137916565,
            0.43486344814300537,
            0.4347889721393585,
            0.4319656193256378,
            0.4319586753845215,
            0.4319427013397217,
            0.4318693280220032,
            0.4318487346172333,
            0.4275011420249939,
            0.4141353964805603,
            0.41379794478416443,
            0.4137427508831024,
            0.41246089339256287,
            0.41229453682899475,
            0.4089027941226959,
            0.40873223543167114,
            0.4084506630897522,
            0.40812191367149353,
            0.4059087634086609,
            0.39791369438171387,
            0.397304892539978,
            0.39691710472106934,
            0.3966933786869049,
            0.3951486647129059,
            0.3947148621082306,
            0.3946673274040222,
            0.39438071846961975,
            0.34985512495040894
          ]
        }
      }
    ]
  },
  "data": {
    "subset_size": 4000,
    "n_components": 8,
    "test_size": 0.3
  }
}